wbal/__init__.py
wbal/agent.py
wbal/bundle.py
wbal/cli.py
wbal/environment.py
wbal/helper.py
wbal/lm.py
wbal/manifests.py
wbal/mixins.py
wbal/object.py
wbal/runner.py
wbal/sandbox_stub.py
wbal/sandboxer.py
wbal/tool_imports.py
wbal/agents/__init__.py
wbal/agents/openai_agent.py
wbal/agents/yaml_agent.py
wbal/environments/__init__.py
wbal/environments/chat_env.py
wbal/environments/configured_env.py
wbal/environments/data_env.py
wbal/environments/poll_env.py
wbal/scripts/__init__.py
wbal/scripts/chat.py
wbal/scripts/poll.py
wbal/tools/__init__.py
wbal/tools/bash.py
wbal-0.6.0.dist-info/METADATA
wbal-0.6.0.dist-info/WHEEL
wbal-0.6.0.dist-info/entry_points.txt
wbal-0.6.0.dist-info/RECORD
