Metadata-Version: 2.4
Name: wbal
Version: 0.6.0
Summary: Weights & Biases Agent Library - A minimal framework for building LLM agents
Requires-Python: <3.14,>=3.13
Requires-Dist: openai<1.100.0,>=1.0.0
Requires-Dist: pydantic>=2.12.5
Requires-Dist: pytest>=9.0.2
Requires-Dist: pyyaml>=6.0.0
Requires-Dist: weave>=0.52.22
